clusx/__init__.py
clusx/__main__.py
clusx/cli.py
clusx/clustering/__init__.py
clusx/clustering/models.py
clusx/clustering/utils.py
clusx/errors.py
clusx/evaluation.py
clusx/logging.py
clusx/utils.py
clusx/version.py
clusx/visualization.py
clusx-0.6.0.dist-info/LICENSE
clusx-0.6.0.dist-info/METADATA
clusx-0.6.0.dist-info/WHEEL
clusx-0.6.0.dist-info/entry_points.txt
clusx-0.6.0.dist-info/RECORD
