Metadata-Version: 2.3
Name: clusx
Version: 0.6.0
Summary: Bayesian nonparametric toolkit for text clustering, analysis, and benchmarking with advanced embedding models and statistical validation.
License: MIT
Keywords: clustering,text-analysis,nlp,natural-language-processing,machine-learning,dirichlet-process,pitman-yor-process,embeddings,sentence-transformers,power-law,data-science
Author: Serghei Iakovlev
Author-email: oss@serghei.pl
Requires-Python: >=3.11,<4
Classifier: Development Status :: 4 - Beta
Classifier: Environment :: Console
Classifier: Intended Audience :: Developers
Classifier: Intended Audience :: Science/Research
Classifier: License :: OSI Approved :: MIT License
Classifier: Natural Language :: English
Classifier: Operating System :: OS Independent
Classifier: Programming Language :: Python
Classifier: Programming Language :: Python :: 3
Classifier: Programming Language :: Python :: 3.11
Classifier: Programming Language :: Python :: 3.12
Classifier: Programming Language :: Python :: 3.13
Classifier: Programming Language :: Python :: Implementation :: CPython
Classifier: Topic :: Scientific/Engineering
Classifier: Topic :: Scientific/Engineering :: Artificial Intelligence
Classifier: Topic :: Scientific/Engineering :: Information Analysis
Classifier: Topic :: Text Processing
Classifier: Topic :: Text Processing :: Linguistic
Classifier: Typing :: Typed
Requires-Dist: click (>=8.1.8,<9.0.0)
Requires-Dist: matplotlib (>=3.10.1,<4.0.0)
Requires-Dist: numpy (>=2.2.3,<3.0.0)
Requires-Dist: pandas (>=2.2.3,<3.0.0)
Requires-Dist: powerlaw (>=1.5,<2.0)
Requires-Dist: scikit-learn (>=1.6.1,<2.0.0)
Requires-Dist: scipy (>=1.15.2,<2.0.0)
Requires-Dist: sentence-transformers (>=3.4.1,<4.0.0)
Requires-Dist: torch (>=2.3.0,<3.0.0)
Requires-Dist: tqdm (>=4.67.1,<5.0.0)
Project-URL: Changelog, https://clusterium.readthedocs.io/en/latest/changelog.html
Project-URL: Documentation, https://clusterium.readthedocs.io/en/latest/index.html
Project-URL: Download, https://github.com/sergeyklay/clusterium/releases
Project-URL: Homepage, https://clusterium.readthedocs.io
Project-URL: Issues, https://github.com/sergeyklay/clusterium/issues
Project-URL: Repository, https://github.com/sergeyklay/clusterium
